pandablocks/__init__.py
pandablocks/__main__.py
pandablocks/_control.py
pandablocks/_exchange.py
pandablocks/_version.py
pandablocks/asyncio.py
pandablocks/blocking.py
pandablocks/cli.py
pandablocks/commands.py
pandablocks/connections.py
pandablocks/hdf.py
pandablocks/responses.py
pandablocks/utils.py
pandablocks/saves/tutorial.sav
pandablocks-0.10.4.dist-info/licenses/LICENSE
pandablocks-0.10.4.dist-info/METADATA
pandablocks-0.10.4.dist-info/WHEEL
pandablocks-0.10.4.dist-info/entry_points.txt
pandablocks-0.10.4.dist-info/top_level.txt
pandablocks-0.10.4.dist-info/RECORD
