Metadata-Version: 2.4
Name: pandablocks
Version: 0.10.4
Summary: A Python client to control and data ports of the PandABlocks TCP server
Author-email: Tom Cobb <tom.cobb@diamond.ac.uk>
License:                                  Apache License
Project-URL: GitHub, https://github.com/PandABlocks/PandABlocks-client
Classifier: Development Status :: 5 - Production/Stable
Classifier: License :: OSI Approved :: Apache Software License
Classifier: Programming Language :: Python :: 3.9
Classifier: Programming Language :: Python :: 3.10
Classifier: Programming Language :: Python :: 3.11
Classifier: Programming Language :: Python :: 3.12
Classifier: Programming Language :: Python :: 3.13
Requires-Python: >=3.9
License-File: LICENSE
Requires-Dist: typing-extensions; python_version < "3.8"
Requires-Dist: numpy
Requires-Dist: click
Provides-Extra: h5py
Requires-Dist: h5py; extra == "h5py"
Requires-Dist: matplotlib; extra == "h5py"
Dynamic: license-file
